myArtists/__init__.py
myArtists/billboard.py
myArtists/melon.py
Artists-0.0.2.dist-info/LICENSE
Artists-0.0.2.dist-info/METADATA
Artists-0.0.2.dist-info/WHEEL
Artists-0.0.2.dist-info/top_level.txt
Artists-0.0.2.dist-info/RECORD
